aipmodel/CephS3Manager.py
aipmodel/__init__.py
aipmodel/model_registry.py
aipmodel/template.py
aipmodel/update_checker.py
aipmodel-0.2.59.dist-info/METADATA
aipmodel-0.2.59.dist-info/WHEEL
aipmodel-0.2.59.dist-info/top_level.txt
aipmodel-0.2.59.dist-info/RECORD
