Metadata-Version: 2.4
Name: aipmodel
Version: 0.2.59
Summary: SDK for model registration, versioning, and storage
Home-page: https://github.com/AIP-MLOPS/model-registry
Author: AIP MLOPS Team
Author-email: mohmmadweb@gmail.com
Requires-Python: >=3.6
Requires-Dist: boto3==1.34.0
Requires-Dist: clearml==2.0.2
Requires-Dist: fastapi==0.111.0
Requires-Dist: hf_xet==1.2.0
Requires-Dist: huggingface-hub==1.1.6
Requires-Dist: pydantic==2.12.5
Requires-Dist: python-dotenv==1.2.1
Requires-Dist: requests==2.32.5
Requires-Dist: tabulate==0.9.0
Requires-Dist: tqdm==4.67.1
Requires-Dist: ruff==0.14.7
Requires-Dist: uvicorn[standard]==0.38.0
Dynamic: author
Dynamic: author-email
Dynamic: home-page
Dynamic: requires-dist
Dynamic: requires-python
Dynamic: summary
